{
	"info": {
		"_postman_id": "bf27ad9d-95f5-4513-8462-3da81f982ffd",
		"name": "cocktail-party",
		"schema": "https://schema.getpostman.com/json/collection/v2.1.0/collection.json",
		"_exporter_id": "24217377"
	},
	"item": [
		{
			"name": "Signup",
			"event": [
				{
					"listen": "test",
					"script": {
						"exec": [
							"var jsonData = JSON.parse(responseBody);",
							"pm.collectionVariables.set(\"accessToken\", jsonData.accessToken);"
						],
						"type": "text/javascript"
					}
				}
			],
			"request": {
				"method": "POST",
				"header": [],
				"body": {
					"mode": "raw",
					"raw": "{\n    \"username\": \"test123\",\n    \"password\": \"pass123!\",\n    \"email\": \"email123@gmail.com\"\n}",
					"options": {
						"raw": {
							"language": "json"
						}
					}
				},
				"url": {
					"raw": "{{host}}/auth/signup",
					"host": [
						"{{host}}"
					],
					"path": [
						"auth",
						"signup"
					]
				}
			},
			"response": []
		},
		{
			"name": "Login",
			"event": [
				{
					"listen": "test",
					"script": {
						"exec": [
							"var jsonData = JSON.parse(responseBody);",
							"pm.collectionVariables.set(\"accessToken\", jsonData.accessToken);"
						],
						"type": "text/javascript"
					}
				}
			],
			"request": {
				"method": "POST",
				"header": [],
				"body": {
					"mode": "raw",
					"raw": "{\n    \"username\": \"test123\",\n    \"password\": \"pass123!\"\n}",
					"options": {
						"raw": {
							"language": "json"
						}
					}
				},
				"url": {
					"raw": "{{host}}/auth/login",
					"host": [
						"{{host}}"
					],
					"path": [
						"auth",
						"login"
					]
				}
			},
			"response": []
		},
		{
			"name": "Healthcheck",
			"event": [
				{
					"listen": "test",
					"script": {
						"exec": [
							""
						],
						"type": "text/javascript"
					}
				}
			],
			"request": {
				"method": "GET",
				"header": [
					{
						"key": "authorization",
						"value": "Bearer {{accessToken}}",
						"type": "text"
					}
				],
				"url": {
					"raw": "{{host}}/healthcheck",
					"host": [
						"{{host}}"
					],
					"path": [
						"healthcheck"
					]
				}
			},
			"response": []
		},
		{
			"name": "List Ingredients",
			"request": {
				"auth": {
					"type": "bearer",
					"bearer": [
						{
							"key": "token",
							"value": "{{accessToken}}",
							"type": "string"
						}
					]
				},
				"method": "GET",
				"header": [],
				"url": {
					"raw": "{{host}}/cocktail_api/list_ingredients",
					"host": [
						"{{host}}"
					],
					"path": [
						"cocktail_api",
						"list_ingredients"
					]
				}
			},
			"response": []
		}
	],
	"event": [
		{
			"listen": "prerequest",
			"script": {
				"type": "text/javascript",
				"exec": [
					""
				]
			}
		},
		{
			"listen": "test",
			"script": {
				"type": "text/javascript",
				"exec": [
					""
				]
			}
		}
	],
	"variable": [
		{
			"key": "accessToken",
			"value": "",
			"type": "string"
		},
		{
			"key": "host",
			"value": "http://localhost:3001",
			"type": "string"
		}
	]
}